histpal/__init__.py
histpal/egypal.py
histpal-0.1.1.dist-info/LICENSE
histpal-0.1.1.dist-info/METADATA
histpal-0.1.1.dist-info/WHEEL
histpal-0.1.1.dist-info/top_level.txt
histpal-0.1.1.dist-info/RECORD
