Metadata-Version: 2.1
Name: histpal
Version: 0.1.1
Summary: A Python library that empowers you to explore and utilize color palettes from various historical civilizations 
Home-page: https://github.com/A7med-7elmy/histpal
Author: Ahmed Helmy
Author-email: Ahmed Helmy <a7med.7assaan@gmail.com>
Project-URL: Homepage, https://github.com/A7med-7elmy/histpal
Project-URL: Issues, https://github.com/A7med-7elmy/histpal/issues
Classifier: Programming Language :: Python :: 3
Classifier: License :: OSI Approved :: Apache Software License
Classifier: Operating System :: OS Independent
Requires-Python: >=3
License-File: LICENSE
